<?xml version="1.0" encoding="utf-8"?>
<ArrayOfUser xmlns:xsi="http://www.w3.org/2001/XMLSchema-instance" xmlns:xsd="http://www.w3.org/2001/XMLSchema">
  <User>
    <ID>415415578</ID>
    <Name>Ali Al-Aziz</Name>
    <Password>QyacTxep</Password>
    <IsManeger>false</IsManeger>
  </User>
  <User>
    <ID>293562674</ID>
    <Name>Ahmed Al-Hamad</Name>
    <Password>MEeSDhz3</Password>
    <IsManeger>false</IsManeger>
  </User>
  <User>
    <ID>546663223</ID>
    <Name>Mohammed Al-Hussein</Name>
    <Password>2RqZTatL</Password>
    <IsManeger>false</IsManeger>
  </User>
  <User>
    <ID>181585038</ID>
    <Name>Hassan Al-Jawad</Name>
    <Password>yviQ2pse</Password>
    <IsManeger>false</IsManeger>
  </User>
  <User>
    <ID>489492045</ID>
    <Name>Omar Al-Mukhtar</Name>
    <Password>ZilMEoJc</Password>
    <IsManeger>false</IsManeger>
  </User>
  <User>
    <ID>951831414</ID>
    <Name>Mahmoud Al-Sharif</Name>
    <Password>1EQ0mxZQ</Password>
    <IsManeger>false</IsManeger>
  </User>
  <User>
    <ID>914308675</ID>
    <Name>Khaled Al-Wazir</Name>
    <Password>tXeOEKfu</Password>
    <IsManeger>false</IsManeger>
  </User>
  <User>
    <ID>448493917</ID>
    <Name>Yousef Al-Zahrani</Name>
    <Password>cWj4qsdN</Password>
    <IsManeger>false</IsManeger>
  </User>
  <User>
    <ID>464780999</ID>
    <Name>Ibrahim Al-Qadi</Name>
    <Password>tPrWTva8</Password>
    <IsManeger>false</IsManeger>
  </User>
  <User>
    <ID>561004333</ID>
    <Name>Li Jian</Name>
    <Password>m28q9r88</Password>
    <IsManeger>false</IsManeger>
  </User>
  <User>
    <ID>659116841</ID>
    <Name>Wang Wei</Name>
    <Password>Ew6tpy7k</Password>
    <IsManeger>false</IsManeger>
  </User>
  <User>
    <ID>960651757</ID>
    <Name>Zhang Xiao</Name>
    <Password>ytqyNJA2</Password>
    <IsManeger>false</IsManeger>
  </User>
  <User>
    <ID>914306830</ID>
    <Name>Zhao Hua</Name>
    <Password>qZyYe15h</Password>
    <IsManeger>false</IsManeger>
  </User>
  <User>
    <ID>290067710</ID>
    <Name>Wu Li</Name>
    <Password>ubtvXREz</Password>
    <IsManeger>false</IsManeger>
  </User>
  <User>
    <ID>721693802</ID>
    <Name>Liu Yan</Name>
    <Password>AjxFqTdR</Password>
    <IsManeger>false</IsManeger>
  </User>
  <User>
    <ID>484920153</ID>
    <Name>Moshe Baruch</Name>
    <Password>12345678</Password>
    <IsManeger>true</IsManeger>
  </User>
  <User>
    <ID>486863664</ID>
    <Name>David Levi</Name>
    <Password>87654321</Password>
    <IsManeger>true</IsManeger>
  </User>
  <User>
    <ID>1234</ID>
    <Name>yosi</Name>
    <Password>5454</Password>
    <IsManeger>true</IsManeger>
  </User>
</ArrayOfUser>