<?xml version="1.0" encoding="utf-8"?>
<ArrayOfUser xmlns:xsi="http://www.w3.org/2001/XMLSchema-instance" xmlns:xsd="http://www.w3.org/2001/XMLSchema">
  <User>
    <ID>704768563</ID>
    <Name>Ali Al-Aziz</Name>
    <Password>hK3F0HGp</Password>
    <IsManeger>false</IsManeger>
  </User>
  <User>
    <ID>986813845</ID>
    <Name>Ahmed Al-Hamad</Name>
    <Password>7bprut18</Password>
    <IsManeger>false</IsManeger>
  </User>
  <User>
    <ID>258004450</ID>
    <Name>Mohammed Al-Hussein</Name>
    <Password>ITwcuOlw</Password>
    <IsManeger>false</IsManeger>
  </User>
  <User>
    <ID>353734443</ID>
    <Name>Hassan Al-Jawad</Name>
    <Password>HVN8l3YY</Password>
    <IsManeger>false</IsManeger>
  </User>
  <User>
    <ID>277651606</ID>
    <Name>Omar Al-Mukhtar</Name>
    <Password>GjIu4EgP</Password>
    <IsManeger>false</IsManeger>
  </User>
  <User>
    <ID>685677004</ID>
    <Name>Mahmoud Al-Sharif</Name>
    <Password>Ay6F0AD4</Password>
    <IsManeger>false</IsManeger>
  </User>
  <User>
    <ID>131605832</ID>
    <Name>Khaled Al-Wazir</Name>
    <Password>SbciNhO2</Password>
    <IsManeger>false</IsManeger>
  </User>
  <User>
    <ID>359633867</ID>
    <Name>Yousef Al-Zahrani</Name>
    <Password>zskwI2IC</Password>
    <IsManeger>false</IsManeger>
  </User>
  <User>
    <ID>975749015</ID>
    <Name>Ibrahim Al-Qadi</Name>
    <Password>Eu68k9En</Password>
    <IsManeger>false</IsManeger>
  </User>
  <User>
    <ID>545360554</ID>
    <Name>Li Jian</Name>
    <Password>LHZzuJEo</Password>
    <IsManeger>false</IsManeger>
  </User>
  <User>
    <ID>420533184</ID>
    <Name>Wang Wei</Name>
    <Password>jqLK67rn</Password>
    <IsManeger>false</IsManeger>
  </User>
  <User>
    <ID>184810290</ID>
    <Name>Zhang Xiao</Name>
    <Password>C1rr3lU1</Password>
    <IsManeger>false</IsManeger>
  </User>
  <User>
    <ID>549542410</ID>
    <Name>Zhao Hua</Name>
    <Password>1v7xdaqi</Password>
    <IsManeger>false</IsManeger>
  </User>
  <User>
    <ID>358044194</ID>
    <Name>Wu Li</Name>
    <Password>m2Jdb7YV</Password>
    <IsManeger>false</IsManeger>
  </User>
  <User>
    <ID>939052539</ID>
    <Name>Liu Yan</Name>
    <Password>txZ8tshI</Password>
    <IsManeger>false</IsManeger>
  </User>
  <User>
    <ID>127809468</ID>
    <Name>Moshe Baruch</Name>
    <Password>12345678</Password>
    <IsManeger>true</IsManeger>
  </User>
  <User>
    <ID>130700147</ID>
    <Name>David Levi</Name>
    <Password>87654321</Password>
    <IsManeger>true</IsManeger>
  </User>
</ArrayOfUser>